LICENSE.txt
MANIFEST.in
NOTICE
README.md
setup.cfg
setup.py
licenses/LICENSE-cal-heatmap.txt
licenses/LICENSE-parallel-coordinates.txt
superset/__init__.py
superset/cli.py
superset/config.py
superset/dataframe.py
superset/db_engine_specs.py
superset/exceptions.py
superset/extract_table_names.py
superset/forms.py
superset/jinja_context.py
superset/legacy.py
superset/security.py
superset/sql_lab.py
superset/sql_parse.py
superset/stats_logger.py
superset/viz.py
superset/bin/__init__.py
superset/bin/superset
superset/common/__init__.py
superset/common/query_context.py
superset/common/query_object.py
superset/connectors/__init__.py
superset/connectors/connector_registry.py
superset/connectors/base/__init__.py
superset/connectors/base/models.py
superset/connectors/base/views.py
superset/connectors/druid/__init__.py
superset/connectors/druid/models.py
superset/connectors/druid/views.py
superset/connectors/sqla/__init__.py
superset/connectors/sqla/models.py
superset/connectors/sqla/views.py
superset/data/__init__.py
superset/data/airports.csv.gz
superset/data/bart-lines.json.gz
superset/data/bart_lines.py
superset/data/birth_france_data_for_country_map.csv
superset/data/birth_names.json.gz
superset/data/birth_names.py
superset/data/countries.json.gz
superset/data/countries.md
superset/data/countries.py
superset/data/country_map.py
superset/data/css_templates.py
superset/data/deck.py
superset/data/energy.json.gz
superset/data/energy.py
superset/data/flight_data.csv.gz
superset/data/flights.py
superset/data/helpers.py
superset/data/long_lat.py
superset/data/misc_dashboard.py
superset/data/multi_line.py
superset/data/multiformat_time_series.json.gz
superset/data/multiformat_time_series.py
superset/data/paris.py
superset/data/paris_iris.json.gz
superset/data/random_time_series.json.gz
superset/data/random_time_series.py
superset/data/san_francisco.csv.gz
superset/data/sf_population.json.gz
superset/data/sf_population_polygons.py
superset/data/unicode_test_data.py
wpt_superset.egg-info/PKG-INFO
wpt_superset.egg-info/SOURCES.txt
wpt_superset.egg-info/dependency_links.txt
wpt_superset.egg-info/not-zip-safe
wpt_superset.egg-info/requires.txt
wpt_superset.egg-info/top_level.txt