Metadata-Version: 2.1
Name: wpt-superset
Version: 1.0.1
Summary: A "Waypoint Telecomunicaciones" version of a modern, enterprise-ready business intelligence web application.
Home-page: https://github.com/leonardo-espinoza/incubator-superset
Author: Waypoint Superset Dev
Author-email: lespinoza@waypoint.cl
License: Apache License, Version 2.0
Download-URL: https://github.com/leonardo-espinoza/incubator-superset/tarball/1.0.1
Platform: UNKNOWN
Classifier: Programming Language :: Python :: 3.6
Provides-Extra: console_log
Provides-Extra: cors
